llm_citation_verifier/__init__.py
llm_citation_verifier/py.typed
llm_citation_verifier/verifier.py
llm_citation_verifier-0.1.2.dist-info/WHEEL
llm_citation_verifier-0.1.2.dist-info/entry_points.txt
llm_citation_verifier-0.1.2.dist-info/METADATA
llm_citation_verifier-0.1.2.dist-info/RECORD
