Metadata-Version: 2.3
Name: llm-citation-verifier
Version: 0.1.2
Summary: LLM plugin for verifying academic citations against Crossref
Author: Dave Flanagan
License: MIT
Requires-Dist: llm>=0.26
Requires-Dist: requests>=2.25.0
Requires-Python: >=3.9
